pony/__init__.py
pony/converting.py
pony/options.py
pony/py23compat.py
pony/flask/__init__.py
pony/flask/example/__init__.py
pony/flask/example/__main__.py
pony/flask/example/app.py
pony/flask/example/config.py
pony/flask/example/models.py
pony/flask/example/views.py
pony/flask/example/templates/index.html
pony/flask/example/templates/login.html
pony/flask/example/templates/reg.html
pony/orm/__init__.py
pony/orm/asttranslation.py
pony/orm/core.py
pony/orm/dbapiprovider.py
pony/orm/dbschema.py
pony/orm/decompiling.py
pony/orm/ormtypes.py
pony/orm/serialization.py
pony/orm/sqlbuilding.py
pony/orm/sqlsymbols.py
pony/orm/sqltranslation.py
pony/orm/dbproviders/__init__.py
pony/orm/dbproviders/cockroach.py
pony/orm/dbproviders/mysql.py
pony/orm/dbproviders/oracle.py
pony/orm/dbproviders/postgres.py
pony/orm/dbproviders/sqlite.py
pony/orm/examples/__init__.py
pony/orm/examples/bottle_example.py
pony/orm/examples/compositekeys.py
pony/orm/examples/demo.py
pony/orm/examples/estore.py
pony/orm/examples/inheritance1.py
pony/orm/examples/test_numbers.py
pony/orm/examples/university1.py
pony/orm/examples/university2.py
pony/orm/integration/__init__.py
pony/orm/integration/bottle_plugin.py
pony/orm/tests/__init__.py
pony/orm/tests/fixtures.py
pony/orm/tests/model1.py
pony/orm/tests/queries.txt
pony/orm/tests/sql_tests.py
pony/orm/tests/test_array.py
pony/orm/tests/test_attribute_options.py
pony/orm/tests/test_autostrip.py
pony/orm/tests/test_buffer.py
pony/orm/tests/test_bug_170.py
pony/orm/tests/test_bug_182.py
pony/orm/tests/test_bug_331.py
pony/orm/tests/test_bug_386.py
pony/orm/tests/test_cascade.py
pony/orm/tests/test_cascade_delete.py
pony/orm/tests/test_collections.py
pony/orm/tests/test_conversions.py
pony/orm/tests/test_core_find_in_cache.py
pony/orm/tests/test_core_multiset.py
pony/orm/tests/test_crud.py
pony/orm/tests/test_crud_raw_sql.py
pony/orm/tests/test_datetime.py
pony/orm/tests/test_db_session.py
pony/orm/tests/test_declarative_attr_set_monad.py
pony2-0.7.16.dist-info/LICENSE
pony2-0.7.16.dist-info/METADATA
pony2-0.7.16.dist-info/WHEEL
pony2-0.7.16.dist-info/top_level.txt
pony2-0.7.16.dist-info/RECORD
