Metadata-Version: 2.1
Name: pony2
Version: 0.7.16
Summary: Pony Object-Relational Mapper
Home-page: https://ponyorm.com
Download-URL: http://pypi.python.org/pypi/pony/
Author: Alexander Kozlovsky <alexander.kozlovsky@gmail.com>, Alexey Malashkevich <alexey@ponyorm.org>, Alexander Tischenko <sashaaero@yandex.ru>
Author-email: team@ponyorm.com
License: Apache License Version 2.0
Project-URL: Documentation, https://docs.ponyorm.org
Project-URL: Source, https://github.com/ponyorm/pony
Classifier: Development Status :: 4 - Beta
Classifier: Intended Audience :: Developers
Classifier: License :: OSI Approved :: Apache Software License
Classifier: Operating System :: OS Independent
Classifier: Programming Language :: Python
Classifier: Programming Language :: Python :: 3
Classifier: Programming Language :: Python :: 3.6
Classifier: Programming Language :: Python :: 3.7
Classifier: Programming Language :: Python :: 3.8
Classifier: Programming Language :: Python :: 3.9
Classifier: Programming Language :: Python :: 3.10
Classifier: Programming Language :: Python :: Implementation :: PyPy
Classifier: Topic :: Software Development :: Libraries
Classifier: Topic :: Database
License-File: LICENSE
